README.md
setup.py
jpot/__init__.py
python_jsonpath_object_transform.egg-info/PKG-INFO
python_jsonpath_object_transform.egg-info/SOURCES.txt
python_jsonpath_object_transform.egg-info/dependency_links.txt
python_jsonpath_object_transform.egg-info/requires.txt
python_jsonpath_object_transform.egg-info/top_level.txt