Metadata-Version: 1.0
Name: python-jsonpath-object-transform
Version: 0.1
Summary: JSON transformation using JSONPath
Home-page: https://github.com/innovationgarage/python-jsonpath-object-transform
Author: Egil Moeller
Author-email: egil@innovationgarage.no
License: UNKNOWN
Platform: UNKNOWN
